epix/__init__.py
epix/betadecay_cluster.py
epix/brem_cluster.py
epix/clustering.py
epix/common.py
epix/detector_volumes.py
epix/detectors.py
epix/electric_field_handler.py
epix/event_separation.py
epix/io.py
epix/quanta_generation.py
epix/quantgen_wrapper.py
epix/run_epix.py
epix-0.3.8.data/scripts/run_epix
epix-0.3.8.dist-info/LICENCE
epix-0.3.8.dist-info/METADATA
epix-0.3.8.dist-info/WHEEL
epix-0.3.8.dist-info/top_level.txt
epix-0.3.8.dist-info/RECORD
