Metadata-Version: 2.1
Name: epix
Version: 0.3.8
Summary: Electron and Photon Instructions generator for XENON
Home-page: https://github.com/XENONnT/epix
Author: epix contributors, the XENON collaboration
License: UNKNOWN
Platform: UNKNOWN
Classifier: Natural Language :: English
Classifier: Programming Language :: Python :: 3.6
Classifier: Intended Audience :: Science/Research
Classifier: Programming Language :: Python :: Implementation :: CPython
Classifier: Topic :: Scientific/Engineering :: Physics
Requires-Python: >=3.6
License-File: LICENCE
Requires-Dist: uproot >=4.0.0
Requires-Dist: awkward >=1.0.0
Requires-Dist: numba !=0.56.0
Requires-Dist: scikit-learn
Requires-Dist: wfsim >=0.7.0
Provides-Extra: docs
Requires-Dist: sphinx ; extra == 'docs'
Requires-Dist: sphinx-rtd-theme ; extra == 'docs'
Requires-Dist: nbsphinx ; extra == 'docs'
Requires-Dist: recommonmark ; extra == 'docs'
Requires-Dist: graphviz ; extra == 'docs'
